Metadata-Version: 2.4
Name: ed_design
Version: 1.3.1
Summary: Python package developed by Envidan A/S scoping to follow the design of the company brand. This package is only for internal use.
Home-page: https://dev.azure.com/EnviDan-AS/ed_design
Author: Martin Vidkjaer
Author-email: mav@envidan.dk
Classifier: Programming Language :: Python :: 3
Classifier: License :: OSI Approved :: MIT License
Classifier: Operating System :: OS Independent
Requires-Python: >3.0.0
Requires-Dist: matplotlib
Requires-Dist: numpy
Requires-Dist: pandas
Requires-Dist: seaborn
Dynamic: author
Dynamic: author-email
Dynamic: classifier
Dynamic: description
Dynamic: description-content-type
Dynamic: home-page
Dynamic: requires-dist
Dynamic: requires-python
Dynamic: summary
